totoml/__init__.py
totoml/cid.py
totoml/concurrent.py
totoml/config.py
totoml/context.py
totoml/controller.py
totoml/delegate.py
totoml/model.py
totoml/version.py
totoml/remote/__init__.py
totoml/remote/gcpstorage.py
totoml/remote/totoml_registry.py
totoml-2.2.3.dist-info/LICENSE
totoml-2.2.3.dist-info/METADATA
totoml-2.2.3.dist-info/WHEEL
totoml-2.2.3.dist-info/top_level.txt
totoml-2.2.3.dist-info/RECORD
