Metadata-Version: 2.1
Name: totoml
Version: 2.2.3
Summary: TotoML SDK for Python
Home-page: https://github.com/nicolasances/py-totoml
Author: nicolasances
Author-email: nicolasances@gmail.com
License: UNKNOWN
Platform: UNKNOWN
Classifier: Programming Language :: Python :: 3
Classifier: License :: OSI Approved :: MIT License
Classifier: Operating System :: OS Independent
Requires-Python: >=3.6
